[
    {
        "Id": 1,
        "EntityType": "Product",
        "PropertyKey": "Name",
        "PropertyValue": "workforce",
        "LanguageId": 1,
        "TableId": 1
    },
    {
        "Id": 2,
        "EntityType": "Product",
        "PropertyKey": "Name",
        "PropertyValue": "interactive",
        "LanguageId": 1,
        "TableId": 2
    },
    {
        "Id": 3,
        "EntityType": "Product",
        "PropertyKey": "Name",
        "PropertyValue": "matrices",
        "LanguageId": 1,
        "TableId": 3
    },
    {
        "Id": 4,
        "EntityType": "Product",
        "PropertyKey": "Name",
        "PropertyValue": "hybrid",
        "LanguageId": 1,
        "TableId": 4
    },
    {
        "Id": 5,
        "EntityType": "Product",
        "PropertyKey": "Name",
        "PropertyValue": "open architecture",
        "LanguageId": 1,
        "TableId": 5
    },
    {
        "Id": 6,
        "EntityType": "Product",
        "PropertyKey": "Name",
        "PropertyValue": "Graphic Interface",
        "LanguageId": 1,
        "TableId": 6
    },
    {
        "Id": 7,
        "EntityType": "Product",
        "PropertyKey": "Name",
        "PropertyValue": "foreground",
        "LanguageId": 1,
        "TableId": 7
    },
    {
        "Id": 8,
        "EntityType": "Product",
        "PropertyKey": "Name",
        "PropertyValue": "multimedia",
        "LanguageId": 1,
        "TableId": 8
    },
    {
        "Id": 9,
        "EntityType": "Product",
        "PropertyKey": "Name",
        "PropertyValue": "asymmetric",
        "LanguageId": 1,
        "TableId": 9
    },
    {
        "Id": 10,
        "EntityType": "Product",
        "PropertyKey": "Name",
        "PropertyValue": "Expanded",
        "LanguageId": 1,
        "TableId": 10
    },
    {
        "Id": 11,
        "EntityType": "Product",
        "PropertyKey": "Name",
        "PropertyValue": "matrix",
        "LanguageId": 1,
        "TableId": 11
    },
    {
        "Id": 12,
        "EntityType": "Product",
        "PropertyKey": "Name",
        "PropertyValue": "Multi-lateral",
        "LanguageId": 1,
        "TableId": 12
    },
    {
        "Id": 13,
        "EntityType": "Product",
        "PropertyKey": "Name",
        "PropertyValue": "matrices",
        "LanguageId": 1,
        "TableId": 13
    },
    {
        "Id": 14,
        "EntityType": "Product",
        "PropertyKey": "Name",
        "PropertyValue": "methodology",
        "LanguageId": 1,
        "TableId": 14
    },
    {
        "Id": 15,
        "EntityType": "Product",
        "PropertyKey": "Name",
        "PropertyValue": "homogeneous",
        "LanguageId": 1,
        "TableId": 15
    },
    {
        "Id": 16,
        "EntityType": "Product",
        "PropertyKey": "Name",
        "PropertyValue": "benchmark",
        "LanguageId": 1,
        "TableId": 16
    },
    {
        "Id": 17,
        "EntityType": "Product",
        "PropertyKey": "Name",
        "PropertyValue": "Secured",
        "LanguageId": 1,
        "TableId": 17
    },
    {
        "Id": 18,
        "EntityType": "Product",
        "PropertyKey": "Name",
        "PropertyValue": "needs-based",
        "LanguageId": 1,
        "TableId": 18
    },
    {
        "Id": 19,
        "EntityType": "Product",
        "PropertyKey": "Name",
        "PropertyValue": "flexibility",
        "LanguageId": 1,
        "TableId": 19
    },
    {
        "Id": 20,
        "EntityType": "Product",
        "PropertyKey": "Name",
        "PropertyValue": "policy",
        "LanguageId": 1,
        "TableId": 20
    },
    {
        "Id": 21,
        "EntityType": "Product",
        "PropertyKey": "Name",
        "PropertyValue": "knowledge base",
        "LanguageId": 1,
        "TableId": 21
    },
    {
        "Id": 22,
        "EntityType": "Product",
        "PropertyKey": "Name",
        "PropertyValue": "real-time",
        "LanguageId": 1,
        "TableId": 22
    },
    {
        "Id": 23,
        "EntityType": "Product",
        "PropertyKey": "Name",
        "PropertyValue": "neutral",
        "LanguageId": 1,
        "TableId": 23
    },
    {
        "Id": 24,
        "EntityType": "Product",
        "PropertyKey": "Name",
        "PropertyValue": "holistic",
        "LanguageId": 1,
        "TableId": 24
    },
    {
        "Id": 25,
        "EntityType": "Product",
        "PropertyKey": "Name",
        "PropertyValue": "mission-critical",
        "LanguageId": 1,
        "TableId": 25
    },
    {
        "Id": 26,
        "EntityType": "Product",
        "PropertyKey": "Name",
        "PropertyValue": "dynamic",
        "LanguageId": 1,
        "TableId": 26
    },
    {
        "Id": 27,
        "EntityType": "Product",
        "PropertyKey": "Name",
        "PropertyValue": "homogeneous",
        "LanguageId": 1,
        "TableId": 27
    },
    {
        "Id": 28,
        "EntityType": "Product",
        "PropertyKey": "Name",
        "PropertyValue": "eco-centric",
        "LanguageId": 1,
        "TableId": 28
    },
    {
        "Id": 29,
        "EntityType": "Product",
        "PropertyKey": "Name",
        "PropertyValue": "framework",
        "LanguageId": 1,
        "TableId": 29
    },
    {
        "Id": 30,
        "EntityType": "Product",
        "PropertyKey": "Name",
        "PropertyValue": "success",
        "LanguageId": 1,
        "TableId": 30
    },
    {
        "Id": 31,
        "EntityType": "Product",
        "PropertyKey": "Name",
        "PropertyValue": "data-warehouse",
        "LanguageId": 1,
        "TableId": 31
    },
    {
        "Id": 32,
        "EntityType": "Product",
        "PropertyKey": "Name",
        "PropertyValue": "standardization",
        "LanguageId": 1,
        "TableId": 32
    },
    {
        "Id": 33,
        "EntityType": "Product",
        "PropertyKey": "Name",
        "PropertyValue": "core",
        "LanguageId": 1,
        "TableId": 33
    },
    {
        "Id": 34,
        "EntityType": "Product",
        "PropertyKey": "Name",
        "PropertyValue": "explicit",
        "LanguageId": 1,
        "TableId": 34
    },
    {
        "Id": 35,
        "EntityType": "Product",
        "PropertyKey": "Name",
        "PropertyValue": "budgetary management",
        "LanguageId": 1,
        "TableId": 35
    },
    {
        "Id": 36,
        "EntityType": "Product",
        "PropertyKey": "Name",
        "PropertyValue": "Devolved",
        "LanguageId": 1,
        "TableId": 36
    },
    {
        "Id": 37,
        "EntityType": "Product",
        "PropertyKey": "Name",
        "PropertyValue": "access",
        "LanguageId": 1,
        "TableId": 37
    },
    {
        "Id": 38,
        "EntityType": "Product",
        "PropertyKey": "Name",
        "PropertyValue": "Extended",
        "LanguageId": 1,
        "TableId": 38
    },
    {
        "Id": 39,
        "EntityType": "Product",
        "PropertyKey": "Name",
        "PropertyValue": "zero administration",
        "LanguageId": 1,
        "TableId": 39
    },
    {
        "Id": 40,
        "EntityType": "Product",
        "PropertyKey": "Name",
        "PropertyValue": "homogeneous",
        "LanguageId": 1,
        "TableId": 40
    },
    {
        "Id": 41,
        "EntityType": "Product",
        "PropertyKey": "Name",
        "PropertyValue": "conglomeration",
        "LanguageId": 1,
        "TableId": 41
    },
    {
        "Id": 42,
        "EntityType": "Product",
        "PropertyKey": "Name",
        "PropertyValue": "interactive",
        "LanguageId": 1,
        "TableId": 42
    },
    {
        "Id": 43,
        "EntityType": "Product",
        "PropertyKey": "Name",
        "PropertyValue": "Down-sized",
        "LanguageId": 1,
        "TableId": 43
    },
    {
        "Id": 44,
        "EntityType": "Product",
        "PropertyKey": "Name",
        "PropertyValue": "dynamic",
        "LanguageId": 1,
        "TableId": 44
    },
    {
        "Id": 45,
        "EntityType": "Product",
        "PropertyKey": "Name",
        "PropertyValue": "Upgradable",
        "LanguageId": 1,
        "TableId": 45
    },
    {
        "Id": 46,
        "EntityType": "Product",
        "PropertyKey": "Name",
        "PropertyValue": "Balanced",
        "LanguageId": 1,
        "TableId": 46
    },
    {
        "Id": 47,
        "EntityType": "Product",
        "PropertyKey": "Name",
        "PropertyValue": "Robust",
        "LanguageId": 1,
        "TableId": 47
    },
    {
        "Id": 48,
        "EntityType": "Product",
        "PropertyKey": "Name",
        "PropertyValue": "functionalities",
        "LanguageId": 1,
        "TableId": 48
    },
    {
        "Id": 49,
        "EntityType": "Product",
        "PropertyKey": "Name",
        "PropertyValue": "client-server",
        "LanguageId": 1,
        "TableId": 49
    },
    {
        "Id": 50,
        "EntityType": "Product",
        "PropertyKey": "Name",
        "PropertyValue": "secondary",
        "LanguageId": 1,
        "TableId": 50
    },
    {
        "Id": 51,
        "EntityType": "Product",
        "PropertyKey": "Name",
        "PropertyValue": "Synchronised",
        "LanguageId": 1,
        "TableId": 51
    },
    {
        "Id": 52,
        "EntityType": "Product",
        "PropertyKey": "Name",
        "PropertyValue": "time-frame",
        "LanguageId": 1,
        "TableId": 52
    },
    {
        "Id": 53,
        "EntityType": "Product",
        "PropertyKey": "Name",
        "PropertyValue": "Self-enabling",
        "LanguageId": 1,
        "TableId": 53
    },
    {
        "Id": 54,
        "EntityType": "Product",
        "PropertyKey": "Name",
        "PropertyValue": "superstructure",
        "LanguageId": 1,
        "TableId": 54
    },
    {
        "Id": 55,
        "EntityType": "Product",
        "PropertyKey": "Name",
        "PropertyValue": "implementation",
        "LanguageId": 1,
        "TableId": 55
    },
    {
        "Id": 56,
        "EntityType": "Product",
        "PropertyKey": "Name",
        "PropertyValue": "multi-tasking",
        "LanguageId": 1,
        "TableId": 56
    },
    {
        "Id": 57,
        "EntityType": "Product",
        "PropertyKey": "Name",
        "PropertyValue": "Enterprise-wide",
        "LanguageId": 1,
        "TableId": 57
    },
    {
        "Id": 58,
        "EntityType": "Product",
        "PropertyKey": "Name",
        "PropertyValue": "dedicated",
        "LanguageId": 1,
        "TableId": 58
    },
    {
        "Id": 59,
        "EntityType": "Product",
        "PropertyKey": "Name",
        "PropertyValue": "context-sensitive",
        "LanguageId": 1,
        "TableId": 59
    },
    {
        "Id": 60,
        "EntityType": "Product",
        "PropertyKey": "Name",
        "PropertyValue": "maximized",
        "LanguageId": 1,
        "TableId": 60
    },
    {
        "Id": 61,
        "EntityType": "Product",
        "PropertyKey": "Name",
        "PropertyValue": "encryption",
        "LanguageId": 1,
        "TableId": 61
    },
    {
        "Id": 62,
        "EntityType": "Product",
        "PropertyKey": "Name",
        "PropertyValue": "modular",
        "LanguageId": 1,
        "TableId": 62
    },
    {
        "Id": 63,
        "EntityType": "Product",
        "PropertyKey": "Name",
        "PropertyValue": "Seamless",
        "LanguageId": 1,
        "TableId": 63
    },
    {
        "Id": 64,
        "EntityType": "Product",
        "PropertyKey": "Name",
        "PropertyValue": "full-range",
        "LanguageId": 1,
        "TableId": 64
    },
    {
        "Id": 65,
        "EntityType": "Product",
        "PropertyKey": "Name",
        "PropertyValue": "6th generation",
        "LanguageId": 1,
        "TableId": 65
    },
    {
        "Id": 66,
        "EntityType": "Product",
        "PropertyKey": "Name",
        "PropertyValue": "Customizable",
        "LanguageId": 1,
        "TableId": 66
    },
    {
        "Id": 67,
        "EntityType": "Product",
        "PropertyKey": "Name",
        "PropertyValue": "bi-directional",
        "LanguageId": 1,
        "TableId": 67
    },
    {
        "Id": 68,
        "EntityType": "Product",
        "PropertyKey": "Name",
        "PropertyValue": "database",
        "LanguageId": 1,
        "TableId": 68
    },
    {
        "Id": 69,
        "EntityType": "Product",
        "PropertyKey": "Name",
        "PropertyValue": "service-desk",
        "LanguageId": 1,
        "TableId": 69
    },
    {
        "Id": 70,
        "EntityType": "Product",
        "PropertyKey": "Name",
        "PropertyValue": "national",
        "LanguageId": 1,
        "TableId": 70
    },
    {
        "Id": 71,
        "EntityType": "Product",
        "PropertyKey": "Name",
        "PropertyValue": "orchestration",
        "LanguageId": 1,
        "TableId": 71
    },
    {
        "Id": 72,
        "EntityType": "Product",
        "PropertyKey": "Name",
        "PropertyValue": "4th generation",
        "LanguageId": 1,
        "TableId": 72
    },
    {
        "Id": 73,
        "EntityType": "Product",
        "PropertyKey": "Name",
        "PropertyValue": "transitional",
        "LanguageId": 1,
        "TableId": 73
    },
    {
        "Id": 74,
        "EntityType": "Product",
        "PropertyKey": "Name",
        "PropertyValue": "matrix",
        "LanguageId": 1,
        "TableId": 74
    },
    {
        "Id": 75,
        "EntityType": "Product",
        "PropertyKey": "Name",
        "PropertyValue": "service-desk",
        "LanguageId": 1,
        "TableId": 75
    },
    {
        "Id": 76,
        "EntityType": "Product",
        "PropertyKey": "Name",
        "PropertyValue": "solution-oriented",
        "LanguageId": 1,
        "TableId": 76
    },
    {
        "Id": 77,
        "EntityType": "Product",
        "PropertyKey": "Name",
        "PropertyValue": "Re-contextualized",
        "LanguageId": 1,
        "TableId": 77
    },
    {
        "Id": 78,
        "EntityType": "Product",
        "PropertyKey": "Name",
        "PropertyValue": "actuating",
        "LanguageId": 1,
        "TableId": 78
    },
    {
        "Id": 79,
        "EntityType": "Product",
        "PropertyKey": "Name",
        "PropertyValue": "synergy",
        "LanguageId": 1,
        "TableId": 79
    },
    {
        "Id": 80,
        "EntityType": "Product",
        "PropertyKey": "Name",
        "PropertyValue": "Multi-tiered",
        "LanguageId": 1,
        "TableId": 80
    },
    {
        "Id": 81,
        "EntityType": "Product",
        "PropertyKey": "Name",
        "PropertyValue": "Horizontal",
        "LanguageId": 1,
        "TableId": 81
    },
    {
        "Id": 82,
        "EntityType": "Product",
        "PropertyKey": "Name",
        "PropertyValue": "composite",
        "LanguageId": 1,
        "TableId": 82
    },
    {
        "Id": 83,
        "EntityType": "Product",
        "PropertyKey": "Name",
        "PropertyValue": "Realigned",
        "LanguageId": 1,
        "TableId": 83
    },
    {
        "Id": 84,
        "EntityType": "Product",
        "PropertyKey": "Name",
        "PropertyValue": "info-mediaries",
        "LanguageId": 1,
        "TableId": 84
    },
    {
        "Id": 85,
        "EntityType": "Product",
        "PropertyKey": "Name",
        "PropertyValue": "fresh-thinking",
        "LanguageId": 1,
        "TableId": 85
    },
    {
        "Id": 86,
        "EntityType": "Product",
        "PropertyKey": "Name",
        "PropertyValue": "architecture",
        "LanguageId": 1,
        "TableId": 86
    },
    {
        "Id": 87,
        "EntityType": "Product",
        "PropertyKey": "Name",
        "PropertyValue": "5th generation",
        "LanguageId": 1,
        "TableId": 87
    },
    {
        "Id": 88,
        "EntityType": "Product",
        "PropertyKey": "Name",
        "PropertyValue": "capability",
        "LanguageId": 1,
        "TableId": 88
    },
    {
        "Id": 89,
        "EntityType": "Product",
        "PropertyKey": "Name",
        "PropertyValue": "Stand-alone",
        "LanguageId": 1,
        "TableId": 89
    },
    {
        "Id": 90,
        "EntityType": "Product",
        "PropertyKey": "Name",
        "PropertyValue": "Reactive",
        "LanguageId": 1,
        "TableId": 90
    },
    {
        "Id": 91,
        "EntityType": "Product",
        "PropertyKey": "Name",
        "PropertyValue": "core",
        "LanguageId": 1,
        "TableId": 91
    },
    {
        "Id": 92,
        "EntityType": "Product",
        "PropertyKey": "Name",
        "PropertyValue": "6th generation",
        "LanguageId": 1,
        "TableId": 92
    },
    {
        "Id": 93,
        "EntityType": "Product",
        "PropertyKey": "Name",
        "PropertyValue": "Public-key",
        "LanguageId": 1,
        "TableId": 93
    },
    {
        "Id": 94,
        "EntityType": "Product",
        "PropertyKey": "Name",
        "PropertyValue": "Secured",
        "LanguageId": 1,
        "TableId": 94
    },
    {
        "Id": 95,
        "EntityType": "Product",
        "PropertyKey": "Name",
        "PropertyValue": "Extended",
        "LanguageId": 1,
        "TableId": 95
    },
    {
        "Id": 96,
        "EntityType": "Product",
        "PropertyKey": "Name",
        "PropertyValue": "De-engineered",
        "LanguageId": 1,
        "TableId": 96
    },
    {
        "Id": 97,
        "EntityType": "Product",
        "PropertyKey": "Name",
        "PropertyValue": "attitude",
        "LanguageId": 1,
        "TableId": 97
    },
    {
        "Id": 98,
        "EntityType": "Product",
        "PropertyKey": "Name",
        "PropertyValue": "Front-line",
        "LanguageId": 1,
        "TableId": 98
    },
    {
        "Id": 99,
        "EntityType": "Product",
        "PropertyKey": "Name",
        "PropertyValue": "web-enabled",
        "LanguageId": 1,
        "TableId": 99
    },
    {
        "Id": 100,
        "EntityType": "Product",
        "PropertyKey": "Name",
        "PropertyValue": "Automated",
        "LanguageId": 1,
        "TableId": 100
    },
    {
        "Id": 101,
        "EntityType": "Product",
        "PropertyKey": "Description",
        "PropertyValue": "laoreet ut rhoncus aliquet pulvinar sed nisl nunc rhoncus dui",
        "LanguageId": 1,
        "TableId": 1
    },
    {
        "Id": 102,
        "EntityType": "Product",
        "PropertyKey": "Description",
        "PropertyValue": "curae donec pharetra magna vestibulum aliquet ultrices erat tortor sollicitudin mi",
        "LanguageId": 1,
        "TableId": 2
    },
    {
        "Id": 103,
        "EntityType": "Product",
        "PropertyKey": "Description",
        "PropertyValue": "nulla mollis molestie lorem quisque ut erat curabitur gravida nisi at nibh",
        "LanguageId": 1,
        "TableId": 3
    },
    {
        "Id": 104,
        "EntityType": "Product",
        "PropertyKey": "Description",
        "PropertyValue": "magna vulputate luctus cum sociis natoque penatibus et magnis dis parturient montes nascetur ridiculus mus vivamus",
        "LanguageId": 1,
        "TableId": 4
    },
    {
        "Id": 105,
        "EntityType": "Product",
        "PropertyKey": "Description",
        "PropertyValue": "phasellus sit amet erat nulla tempus vivamus in felis eu",
        "LanguageId": 1,
        "TableId": 5
    },
    {
        "Id": 106,
        "EntityType": "Product",
        "PropertyKey": "Description",
        "PropertyValue": "ut at dolor quis odio consequat varius integer ac leo pellentesque ultrices",
        "LanguageId": 1,
        "TableId": 6
    },
    {
        "Id": 107,
        "EntityType": "Product",
        "PropertyKey": "Description",
        "PropertyValue": "donec ut dolor morbi vel lectus in quam fringilla rhoncus mauris enim leo rhoncus sed vestibulum sit amet",
        "LanguageId": 1,
        "TableId": 7
    },
    {
        "Id": 108,
        "EntityType": "Product",
        "PropertyKey": "Description",
        "PropertyValue": "nulla sed vel enim sit amet nunc viverra dapibus nulla suscipit ligula in lacus",
        "LanguageId": 1,
        "TableId": 8
    },
    {
        "Id": 109,
        "EntityType": "Product",
        "PropertyKey": "Description",
        "PropertyValue": "tortor id nulla ultrices aliquet maecenas leo odio condimentum id",
        "LanguageId": 1,
        "TableId": 9
    },
    {
        "Id": 110,
        "EntityType": "Product",
        "PropertyKey": "Description",
        "PropertyValue": "scelerisque quam turpis adipiscing lorem vitae mattis nibh ligula nec sem duis aliquam convallis",
        "LanguageId": 1,
        "TableId": 10
    },
    {
        "Id": 111,
        "EntityType": "Product",
        "PropertyKey": "Description",
        "PropertyValue": "curae donec pharetra magna vestibulum aliquet ultrices erat tortor sollicitudin mi sit amet lobortis sapien",
        "LanguageId": 1,
        "TableId": 11
    },
    {
        "Id": 112,
        "EntityType": "Product",
        "PropertyKey": "Description",
        "PropertyValue": "sagittis nam congue risus semper porta volutpat quam pede lobortis",
        "LanguageId": 1,
        "TableId": 12
    },
    {
        "Id": 113,
        "EntityType": "Product",
        "PropertyKey": "Description",
        "PropertyValue": "in purus eu magna vulputate luctus cum sociis natoque penatibus et magnis dis parturient montes nascetur ridiculus mus vivamus vestibulum",
        "LanguageId": 1,
        "TableId": 13
    },
    {
        "Id": 114,
        "EntityType": "Product",
        "PropertyKey": "Description",
        "PropertyValue": "nisl ut volutpat sapien arcu sed augue aliquam erat volutpat in congue etiam justo etiam pretium iaculis justo",
        "LanguageId": 1,
        "TableId": 14
    },
    {
        "Id": 115,
        "EntityType": "Product",
        "PropertyKey": "Description",
        "PropertyValue": "lacinia aenean sit amet justo morbi ut odio cras mi pede malesuada in imperdiet et commodo vulputate justo",
        "LanguageId": 1,
        "TableId": 15
    },
    {
        "Id": 116,
        "EntityType": "Product",
        "PropertyKey": "Description",
        "PropertyValue": "posuere cubilia curae nulla dapibus dolor vel est donec odio justo sollicitudin ut suscipit a feugiat et eros",
        "LanguageId": 1,
        "TableId": 16
    },
    {
        "Id": 117,
        "EntityType": "Product",
        "PropertyKey": "Description",
        "PropertyValue": "eu magna vulputate luctus cum sociis natoque penatibus et magnis dis parturient",
        "LanguageId": 1,
        "TableId": 17
    },
    {
        "Id": 118,
        "EntityType": "Product",
        "PropertyKey": "Description",
        "PropertyValue": "cras in purus eu magna vulputate luctus cum sociis natoque penatibus",
        "LanguageId": 1,
        "TableId": 18
    },
    {
        "Id": 119,
        "EntityType": "Product",
        "PropertyKey": "Description",
        "PropertyValue": "amet consectetuer adipiscing elit proin risus praesent lectus vestibulum quam sapien",
        "LanguageId": 1,
        "TableId": 19
    },
    {
        "Id": 120,
        "EntityType": "Product",
        "PropertyKey": "Description",
        "PropertyValue": "ut blandit non interdum in ante vestibulum ante ipsum primis in faucibus orci luctus et",
        "LanguageId": 1,
        "TableId": 20
    },
    {
        "Id": 121,
        "EntityType": "Product",
        "PropertyKey": "Description",
        "PropertyValue": "in hac habitasse platea dictumst maecenas ut massa quis augue luctus tincidunt nulla",
        "LanguageId": 1,
        "TableId": 21
    },
    {
        "Id": 122,
        "EntityType": "Product",
        "PropertyKey": "Description",
        "PropertyValue": "luctus rutrum nulla tellus in sagittis dui vel nisl duis ac nibh fusce lacus purus aliquet at feugiat non pretium",
        "LanguageId": 1,
        "TableId": 22
    },
    {
        "Id": 123,
        "EntityType": "Product",
        "PropertyKey": "Description",
        "PropertyValue": "habitasse platea dictumst maecenas ut massa quis augue luctus tincidunt nulla",
        "LanguageId": 1,
        "TableId": 23
    },
    {
        "Id": 124,
        "EntityType": "Product",
        "PropertyKey": "Description",
        "PropertyValue": "in imperdiet et commodo vulputate justo in blandit ultrices enim lorem ipsum dolor sit amet consectetuer adipiscing elit",
        "LanguageId": 1,
        "TableId": 24
    },
    {
        "Id": 125,
        "EntityType": "Product",
        "PropertyKey": "Description",
        "PropertyValue": "nunc nisl duis bibendum felis sed interdum venenatis turpis enim blandit mi in porttitor pede justo eu massa",
        "LanguageId": 1,
        "TableId": 25
    },
    {
        "Id": 126,
        "EntityType": "Product",
        "PropertyKey": "Description",
        "PropertyValue": "etiam pretium iaculis justo in hac habitasse platea dictumst etiam faucibus cursus urna",
        "LanguageId": 1,
        "TableId": 26
    },
    {
        "Id": 127,
        "EntityType": "Product",
        "PropertyKey": "Description",
        "PropertyValue": "quis odio consequat varius integer ac leo pellentesque ultrices mattis odio donec",
        "LanguageId": 1,
        "TableId": 27
    },
    {
        "Id": 128,
        "EntityType": "Product",
        "PropertyKey": "Description",
        "PropertyValue": "molestie nibh in lectus pellentesque at nulla suspendisse potenti cras in purus eu magna",
        "LanguageId": 1,
        "TableId": 28
    },
    {
        "Id": 129,
        "EntityType": "Product",
        "PropertyKey": "Description",
        "PropertyValue": "ultrices posuere cubilia curae donec pharetra magna vestibulum aliquet ultrices",
        "LanguageId": 1,
        "TableId": 29
    },
    {
        "Id": 130,
        "EntityType": "Product",
        "PropertyKey": "Description",
        "PropertyValue": "nulla tempus vivamus in felis eu sapien cursus vestibulum proin eu mi nulla ac enim in tempor",
        "LanguageId": 1,
        "TableId": 30
    },
    {
        "Id": 131,
        "EntityType": "Product",
        "PropertyKey": "Description",
        "PropertyValue": "pellentesque eget nunc donec quis orci eget orci vehicula condimentum curabitur in libero ut massa volutpat convallis",
        "LanguageId": 1,
        "TableId": 31
    },
    {
        "Id": 132,
        "EntityType": "Product",
        "PropertyKey": "Description",
        "PropertyValue": "justo etiam pretium iaculis justo in hac habitasse platea dictumst etiam faucibus cursus urna ut",
        "LanguageId": 1,
        "TableId": 32
    },
    {
        "Id": 133,
        "EntityType": "Product",
        "PropertyKey": "Description",
        "PropertyValue": "montes nascetur ridiculus mus vivamus vestibulum sagittis sapien cum sociis natoque penatibus et magnis dis",
        "LanguageId": 1,
        "TableId": 33
    },
    {
        "Id": 134,
        "EntityType": "Product",
        "PropertyKey": "Description",
        "PropertyValue": "est risus auctor sed tristique in tempus sit amet sem fusce consequat nulla nisl nunc nisl duis bibendum felis",
        "LanguageId": 1,
        "TableId": 34
    },
    {
        "Id": 135,
        "EntityType": "Product",
        "PropertyKey": "Description",
        "PropertyValue": "sem fusce consequat nulla nisl nunc nisl duis bibendum felis sed interdum venenatis turpis enim blandit mi in porttitor",
        "LanguageId": 1,
        "TableId": 35
    },
    {
        "Id": 136,
        "EntityType": "Product",
        "PropertyKey": "Description",
        "PropertyValue": "commodo placerat praesent blandit nam nulla integer pede justo lacinia eget tincidunt eget tempus vel pede morbi porttitor lorem",
        "LanguageId": 1,
        "TableId": 36
    },
    {
        "Id": 137,
        "EntityType": "Product",
        "PropertyKey": "Description",
        "PropertyValue": "vestibulum sagittis sapien cum sociis natoque penatibus et magnis dis",
        "LanguageId": 1,
        "TableId": 37
    },
    {
        "Id": 138,
        "EntityType": "Product",
        "PropertyKey": "Description",
        "PropertyValue": "in hac habitasse platea dictumst aliquam augue quam sollicitudin vitae consectetuer eget rutrum at lorem",
        "LanguageId": 1,
        "TableId": 38
    },
    {
        "Id": 139,
        "EntityType": "Product",
        "PropertyKey": "Description",
        "PropertyValue": "molestie lorem quisque ut erat curabitur gravida nisi at nibh",
        "LanguageId": 1,
        "TableId": 39
    },
    {
        "Id": 140,
        "EntityType": "Product",
        "PropertyKey": "Description",
        "PropertyValue": "vulputate vitae nisl aenean lectus pellentesque eget nunc donec quis orci eget orci",
        "LanguageId": 1,
        "TableId": 40
    },
    {
        "Id": 141,
        "EntityType": "Product",
        "PropertyKey": "Description",
        "PropertyValue": "vivamus metus arcu adipiscing molestie hendrerit at vulputate vitae nisl aenean lectus pellentesque eget nunc donec quis orci eget orci",
        "LanguageId": 1,
        "TableId": 41
    },
    {
        "Id": 142,
        "EntityType": "Product",
        "PropertyKey": "Description",
        "PropertyValue": "id consequat in consequat ut nulla sed accumsan felis ut at dolor",
        "LanguageId": 1,
        "TableId": 42
    },
    {
        "Id": 143,
        "EntityType": "Product",
        "PropertyKey": "Description",
        "PropertyValue": "adipiscing molestie hendrerit at vulputate vitae nisl aenean lectus pellentesque eget nunc donec quis orci eget orci vehicula condimentum",
        "LanguageId": 1,
        "TableId": 43
    },
    {
        "Id": 144,
        "EntityType": "Product",
        "PropertyKey": "Description",
        "PropertyValue": "nonummy integer non velit donec diam neque vestibulum eget vulputate ut ultrices vel augue vestibulum ante ipsum primis",
        "LanguageId": 1,
        "TableId": 44
    },
    {
        "Id": 145,
        "EntityType": "Product",
        "PropertyKey": "Description",
        "PropertyValue": "nisl duis ac nibh fusce lacus purus aliquet at feugiat non pretium quis lectus suspendisse potenti in eleifend quam a",
        "LanguageId": 1,
        "TableId": 45
    },
    {
        "Id": 146,
        "EntityType": "Product",
        "PropertyKey": "Description",
        "PropertyValue": "congue vivamus metus arcu adipiscing molestie hendrerit at vulputate vitae nisl aenean lectus pellentesque eget nunc donec",
        "LanguageId": 1,
        "TableId": 46
    },
    {
        "Id": 147,
        "EntityType": "Product",
        "PropertyKey": "Description",
        "PropertyValue": "ipsum primis in faucibus orci luctus et ultrices posuere cubilia",
        "LanguageId": 1,
        "TableId": 47
    },
    {
        "Id": 148,
        "EntityType": "Product",
        "PropertyKey": "Description",
        "PropertyValue": "dolor vel est donec odio justo sollicitudin ut suscipit a feugiat",
        "LanguageId": 1,
        "TableId": 48
    },
    {
        "Id": 149,
        "EntityType": "Product",
        "PropertyKey": "Description",
        "PropertyValue": "nibh in quis justo maecenas rhoncus aliquam lacus morbi quis tortor id nulla ultrices aliquet maecenas leo odio condimentum id",
        "LanguageId": 1,
        "TableId": 49
    },
    {
        "Id": 150,
        "EntityType": "Product",
        "PropertyKey": "Description",
        "PropertyValue": "nisi at nibh in hac habitasse platea dictumst aliquam augue quam",
        "LanguageId": 1,
        "TableId": 50
    },
    {
        "Id": 151,
        "EntityType": "Product",
        "PropertyKey": "Description",
        "PropertyValue": "eu interdum eu tincidunt in leo maecenas pulvinar lobortis est phasellus sit amet erat nulla tempus vivamus in",
        "LanguageId": 1,
        "TableId": 51
    },
    {
        "Id": 152,
        "EntityType": "Product",
        "PropertyKey": "Description",
        "PropertyValue": "felis fusce posuere felis sed lacus morbi sem mauris laoreet ut rhoncus aliquet pulvinar sed nisl nunc rhoncus dui vel",
        "LanguageId": 1,
        "TableId": 52
    },
    {
        "Id": 153,
        "EntityType": "Product",
        "PropertyKey": "Description",
        "PropertyValue": "dictumst etiam faucibus cursus urna ut tellus nulla ut erat id mauris vulputate elementum nullam varius nulla facilisi cras",
        "LanguageId": 1,
        "TableId": 53
    },
    {
        "Id": 154,
        "EntityType": "Product",
        "PropertyKey": "Description",
        "PropertyValue": "eget nunc donec quis orci eget orci vehicula condimentum curabitur in libero ut massa volutpat",
        "LanguageId": 1,
        "TableId": 54
    },
    {
        "Id": 155,
        "EntityType": "Product",
        "PropertyKey": "Description",
        "PropertyValue": "eros viverra eget congue eget semper rutrum nulla nunc purus",
        "LanguageId": 1,
        "TableId": 55
    },
    {
        "Id": 156,
        "EntityType": "Product",
        "PropertyKey": "Description",
        "PropertyValue": "pellentesque ultrices mattis odio donec vitae nisi nam ultrices libero non mattis pulvinar nulla pede ullamcorper augue a suscipit",
        "LanguageId": 1,
        "TableId": 56
    },
    {
        "Id": 157,
        "EntityType": "Product",
        "PropertyKey": "Description",
        "PropertyValue": "ridiculus mus etiam vel augue vestibulum rutrum rutrum neque aenean auctor gravida sem praesent id massa id",
        "LanguageId": 1,
        "TableId": 57
    },
    {
        "Id": 158,
        "EntityType": "Product",
        "PropertyKey": "Description",
        "PropertyValue": "cursus id turpis integer aliquet massa id lobortis convallis tortor risus dapibus augue vel accumsan tellus nisi eu orci",
        "LanguageId": 1,
        "TableId": 58
    },
    {
        "Id": 159,
        "EntityType": "Product",
        "PropertyKey": "Description",
        "PropertyValue": "amet consectetuer adipiscing elit proin interdum mauris non ligula pellentesque ultrices phasellus",
        "LanguageId": 1,
        "TableId": 59
    },
    {
        "Id": 160,
        "EntityType": "Product",
        "PropertyKey": "Description",
        "PropertyValue": "erat fermentum justo nec condimentum neque sapien placerat ante nulla justo aliquam quis turpis eget elit sodales scelerisque",
        "LanguageId": 1,
        "TableId": 60
    },
    {
        "Id": 161,
        "EntityType": "Product",
        "PropertyKey": "Description",
        "PropertyValue": "mattis odio donec vitae nisi nam ultrices libero non mattis pulvinar nulla pede ullamcorper",
        "LanguageId": 1,
        "TableId": 61
    },
    {
        "Id": 162,
        "EntityType": "Product",
        "PropertyKey": "Description",
        "PropertyValue": "pellentesque viverra pede ac diam cras pellentesque volutpat dui maecenas tristique est et",
        "LanguageId": 1,
        "TableId": 62
    },
    {
        "Id": 163,
        "EntityType": "Product",
        "PropertyKey": "Description",
        "PropertyValue": "erat curabitur gravida nisi at nibh in hac habitasse platea",
        "LanguageId": 1,
        "TableId": 63
    },
    {
        "Id": 164,
        "EntityType": "Product",
        "PropertyKey": "Description",
        "PropertyValue": "nullam sit amet turpis elementum ligula vehicula consequat morbi a ipsum",
        "LanguageId": 1,
        "TableId": 64
    },
    {
        "Id": 165,
        "EntityType": "Product",
        "PropertyKey": "Description",
        "PropertyValue": "in eleifend quam a odio in hac habitasse platea dictumst maecenas ut massa quis augue luctus tincidunt nulla",
        "LanguageId": 1,
        "TableId": 65
    },
    {
        "Id": 166,
        "EntityType": "Product",
        "PropertyKey": "Description",
        "PropertyValue": "potenti in eleifend quam a odio in hac habitasse platea dictumst maecenas",
        "LanguageId": 1,
        "TableId": 66
    },
    {
        "Id": 167,
        "EntityType": "Product",
        "PropertyKey": "Description",
        "PropertyValue": "amet eleifend pede libero quis orci nullam molestie nibh in lectus pellentesque at nulla suspendisse",
        "LanguageId": 1,
        "TableId": 67
    },
    {
        "Id": 168,
        "EntityType": "Product",
        "PropertyKey": "Description",
        "PropertyValue": "semper rutrum nulla nunc purus phasellus in felis donec semper sapien a libero nam dui proin",
        "LanguageId": 1,
        "TableId": 68
    },
    {
        "Id": 169,
        "EntityType": "Product",
        "PropertyKey": "Description",
        "PropertyValue": "etiam faucibus cursus urna ut tellus nulla ut erat id mauris",
        "LanguageId": 1,
        "TableId": 69
    },
    {
        "Id": 170,
        "EntityType": "Product",
        "PropertyKey": "Description",
        "PropertyValue": "nullam varius nulla facilisi cras non velit nec nisi vulputate nonummy maecenas tincidunt",
        "LanguageId": 1,
        "TableId": 70
    },
    {
        "Id": 171,
        "EntityType": "Product",
        "PropertyKey": "Description",
        "PropertyValue": "ut odio cras mi pede malesuada in imperdiet et commodo vulputate justo in blandit ultrices enim lorem",
        "LanguageId": 1,
        "TableId": 71
    },
    {
        "Id": 172,
        "EntityType": "Product",
        "PropertyKey": "Description",
        "PropertyValue": "quam nec dui luctus rutrum nulla tellus in sagittis dui vel",
        "LanguageId": 1,
        "TableId": 72
    },
    {
        "Id": 173,
        "EntityType": "Product",
        "PropertyKey": "Description",
        "PropertyValue": "habitasse platea dictumst morbi vestibulum velit id pretium iaculis diam erat fermentum justo nec condimentum neque",
        "LanguageId": 1,
        "TableId": 73
    },
    {
        "Id": 174,
        "EntityType": "Product",
        "PropertyKey": "Description",
        "PropertyValue": "metus arcu adipiscing molestie hendrerit at vulputate vitae nisl aenean lectus pellentesque eget nunc donec quis",
        "LanguageId": 1,
        "TableId": 74
    },
    {
        "Id": 175,
        "EntityType": "Product",
        "PropertyKey": "Description",
        "PropertyValue": "lobortis sapien sapien non mi integer ac neque duis bibendum morbi non quam nec dui luctus",
        "LanguageId": 1,
        "TableId": 75
    },
    {
        "Id": 176,
        "EntityType": "Product",
        "PropertyKey": "Description",
        "PropertyValue": "donec ut dolor morbi vel lectus in quam fringilla rhoncus",
        "LanguageId": 1,
        "TableId": 76
    },
    {
        "Id": 177,
        "EntityType": "Product",
        "PropertyKey": "Description",
        "PropertyValue": "vestibulum rutrum rutrum neque aenean auctor gravida sem praesent id",
        "LanguageId": 1,
        "TableId": 77
    },
    {
        "Id": 178,
        "EntityType": "Product",
        "PropertyKey": "Description",
        "PropertyValue": "amet eleifend pede libero quis orci nullam molestie nibh in lectus pellentesque at",
        "LanguageId": 1,
        "TableId": 78
    },
    {
        "Id": 179,
        "EntityType": "Product",
        "PropertyKey": "Description",
        "PropertyValue": "aliquam sit amet diam in magna bibendum imperdiet nullam orci",
        "LanguageId": 1,
        "TableId": 79
    },
    {
        "Id": 180,
        "EntityType": "Product",
        "PropertyKey": "Description",
        "PropertyValue": "augue vel accumsan tellus nisi eu orci mauris lacinia sapien quis libero nullam",
        "LanguageId": 1,
        "TableId": 80
    },
    {
        "Id": 181,
        "EntityType": "Product",
        "PropertyKey": "Description",
        "PropertyValue": "elit proin interdum mauris non ligula pellentesque ultrices phasellus id",
        "LanguageId": 1,
        "TableId": 81
    },
    {
        "Id": 182,
        "EntityType": "Product",
        "PropertyKey": "Description",
        "PropertyValue": "ac consequat metus sapien ut nunc vestibulum ante ipsum primis in faucibus orci luctus",
        "LanguageId": 1,
        "TableId": 82
    },
    {
        "Id": 183,
        "EntityType": "Product",
        "PropertyKey": "Description",
        "PropertyValue": "cursus id turpis integer aliquet massa id lobortis convallis tortor risus dapibus augue",
        "LanguageId": 1,
        "TableId": 83
    },
    {
        "Id": 184,
        "EntityType": "Product",
        "PropertyKey": "Description",
        "PropertyValue": "purus phasellus in felis donec semper sapien a libero nam",
        "LanguageId": 1,
        "TableId": 84
    },
    {
        "Id": 185,
        "EntityType": "Product",
        "PropertyKey": "Description",
        "PropertyValue": "in hac habitasse platea dictumst maecenas ut massa quis augue luctus tincidunt nulla mollis molestie",
        "LanguageId": 1,
        "TableId": 85
    },
    {
        "Id": 186,
        "EntityType": "Product",
        "PropertyKey": "Description",
        "PropertyValue": "justo maecenas rhoncus aliquam lacus morbi quis tortor id nulla ultrices aliquet maecenas leo odio condimentum id luctus nec molestie",
        "LanguageId": 1,
        "TableId": 86
    },
    {
        "Id": 187,
        "EntityType": "Product",
        "PropertyKey": "Description",
        "PropertyValue": "pellentesque quisque porta volutpat erat quisque erat eros viverra eget congue eget semper rutrum nulla nunc",
        "LanguageId": 1,
        "TableId": 87
    },
    {
        "Id": 188,
        "EntityType": "Product",
        "PropertyKey": "Description",
        "PropertyValue": "aliquam convallis nunc proin at turpis a pede posuere nonummy integer non velit donec diam",
        "LanguageId": 1,
        "TableId": 88
    },
    {
        "Id": 189,
        "EntityType": "Product",
        "PropertyKey": "Description",
        "PropertyValue": "justo nec condimentum neque sapien placerat ante nulla justo aliquam quis turpis eget elit sodales scelerisque mauris sit",
        "LanguageId": 1,
        "TableId": 89
    },
    {
        "Id": 190,
        "EntityType": "Product",
        "PropertyKey": "Description",
        "PropertyValue": "non velit donec diam neque vestibulum eget vulputate ut ultrices vel augue vestibulum ante ipsum primis in faucibus orci",
        "LanguageId": 1,
        "TableId": 90
    },
    {
        "Id": 191,
        "EntityType": "Product",
        "PropertyKey": "Description",
        "PropertyValue": "sed magna at nunc commodo placerat praesent blandit nam nulla integer pede justo lacinia",
        "LanguageId": 1,
        "TableId": 91
    },
    {
        "Id": 192,
        "EntityType": "Product",
        "PropertyKey": "Description",
        "PropertyValue": "vestibulum aliquet ultrices erat tortor sollicitudin mi sit amet lobortis sapien sapien",
        "LanguageId": 1,
        "TableId": 92
    },
    {
        "Id": 193,
        "EntityType": "Product",
        "PropertyKey": "Description",
        "PropertyValue": "sit amet eros suspendisse accumsan tortor quis turpis sed ante vivamus tortor duis mattis egestas metus aenean fermentum donec",
        "LanguageId": 1,
        "TableId": 93
    },
    {
        "Id": 194,
        "EntityType": "Product",
        "PropertyKey": "Description",
        "PropertyValue": "condimentum neque sapien placerat ante nulla justo aliquam quis turpis eget elit sodales scelerisque",
        "LanguageId": 1,
        "TableId": 94
    },
    {
        "Id": 195,
        "EntityType": "Product",
        "PropertyKey": "Description",
        "PropertyValue": "tempus sit amet sem fusce consequat nulla nisl nunc nisl duis",
        "LanguageId": 1,
        "TableId": 95
    },
    {
        "Id": 196,
        "EntityType": "Product",
        "PropertyKey": "Description",
        "PropertyValue": "pellentesque ultrices phasellus id sapien in sapien iaculis congue vivamus metus arcu adipiscing molestie hendrerit at vulputate",
        "LanguageId": 1,
        "TableId": 96
    },
    {
        "Id": 197,
        "EntityType": "Product",
        "PropertyKey": "Description",
        "PropertyValue": "pede venenatis non sodales sed tincidunt eu felis fusce posuere felis sed",
        "LanguageId": 1,
        "TableId": 97
    },
    {
        "Id": 198,
        "EntityType": "Product",
        "PropertyKey": "Description",
        "PropertyValue": "massa volutpat convallis morbi odio odio elementum eu interdum eu tincidunt in leo maecenas",
        "LanguageId": 1,
        "TableId": 98
    },
    {
        "Id": 199,
        "EntityType": "Product",
        "PropertyKey": "Description",
        "PropertyValue": "sed interdum venenatis turpis enim blandit mi in porttitor pede",
        "LanguageId": 1,
        "TableId": 99
    },
    {
        "Id": 200,
        "EntityType": "Product",
        "PropertyKey": "Description",
        "PropertyValue": "amet nulla quisque arcu libero rutrum ac lobortis vel dapibus at diam nam tristique tortor",
        "LanguageId": 1,
        "TableId": 100
    },
    {
        "Id": 201,
        "EntityType": "Product",
        "PropertyKey": "Name",
        "PropertyValue": "婧涵",
        "LanguageId": 2,
        "TableId": 1
    },
    {
        "Id": 202,
        "EntityType": "Product",
        "PropertyKey": "Name",
        "PropertyValue": "海程",
        "LanguageId": 2,
        "TableId": 2
    },
    {
        "Id": 203,
        "EntityType": "Product",
        "PropertyKey": "Name",
        "PropertyValue": "孜绍",
        "LanguageId": 2,
        "TableId": 3
    },
    {
        "Id": 204,
        "EntityType": "Product",
        "PropertyKey": "Name",
        "PropertyValue": "宇涵",
        "LanguageId": 2,
        "TableId": 4
    },
    {
        "Id": 205,
        "EntityType": "Product",
        "PropertyKey": "Name",
        "PropertyValue": "佐仪",
        "LanguageId": 2,
        "TableId": 5
    },
    {
        "Id": 206,
        "EntityType": "Product",
        "PropertyKey": "Name",
        "PropertyValue": "笑薇",
        "LanguageId": 2,
        "TableId": 6
    },
    {
        "Id": 207,
        "EntityType": "Product",
        "PropertyKey": "Name",
        "PropertyValue": "茹雪",
        "LanguageId": 2,
        "TableId": 7
    },
    {
        "Id": 208,
        "EntityType": "Product",
        "PropertyKey": "Name",
        "PropertyValue": "轩硕",
        "LanguageId": 2,
        "TableId": 8
    },
    {
        "Id": 209,
        "EntityType": "Product",
        "PropertyKey": "Name",
        "PropertyValue": "晓烽",
        "LanguageId": 2,
        "TableId": 9
    },
    {
        "Id": 210,
        "EntityType": "Product",
        "PropertyKey": "Name",
        "PropertyValue": "月婵",
        "LanguageId": 2,
        "TableId": 10
    },
    {
        "Id": 211,
        "EntityType": "Product",
        "PropertyKey": "Name",
        "PropertyValue": "军卿",
        "LanguageId": 2,
        "TableId": 11
    },
    {
        "Id": 212,
        "EntityType": "Product",
        "PropertyKey": "Name",
        "PropertyValue": "宸瑜",
        "LanguageId": 2,
        "TableId": 12
    },
    {
        "Id": 213,
        "EntityType": "Product",
        "PropertyKey": "Name",
        "PropertyValue": "崇杉",
        "LanguageId": 2,
        "TableId": 13
    },
    {
        "Id": 214,
        "EntityType": "Product",
        "PropertyKey": "Name",
        "PropertyValue": "宇涵",
        "LanguageId": 2,
        "TableId": 14
    },
    {
        "Id": 215,
        "EntityType": "Product",
        "PropertyKey": "Name",
        "PropertyValue": "梓焓",
        "LanguageId": 2,
        "TableId": 15
    },
    {
        "Id": 216,
        "EntityType": "Product",
        "PropertyKey": "Name",
        "PropertyValue": "婧琪",
        "LanguageId": 2,
        "TableId": 16
    },
    {
        "Id": 217,
        "EntityType": "Product",
        "PropertyKey": "Name",
        "PropertyValue": "雪怡",
        "LanguageId": 2,
        "TableId": 17
    },
    {
        "Id": 218,
        "EntityType": "Product",
        "PropertyKey": "Name",
        "PropertyValue": "雪怡",
        "LanguageId": 2,
        "TableId": 18
    },
    {
        "Id": 219,
        "EntityType": "Product",
        "PropertyKey": "Name",
        "PropertyValue": "墨含",
        "LanguageId": 2,
        "TableId": 19
    },
    {
        "Id": 220,
        "EntityType": "Product",
        "PropertyKey": "Name",
        "PropertyValue": "雨萌",
        "LanguageId": 2,
        "TableId": 20
    },
    {
        "Id": 221,
        "EntityType": "Product",
        "PropertyKey": "Name",
        "PropertyValue": "羽彤",
        "LanguageId": 2,
        "TableId": 21
    },
    {
        "Id": 222,
        "EntityType": "Product",
        "PropertyKey": "Name",
        "PropertyValue": "璟雯",
        "LanguageId": 2,
        "TableId": 22
    },
    {
        "Id": 223,
        "EntityType": "Product",
        "PropertyKey": "Name",
        "PropertyValue": "秩选",
        "LanguageId": 2,
        "TableId": 23
    },
    {
        "Id": 224,
        "EntityType": "Product",
        "PropertyKey": "Name",
        "PropertyValue": "墨含",
        "LanguageId": 2,
        "TableId": 24
    },
    {
        "Id": 225,
        "EntityType": "Product",
        "PropertyKey": "Name",
        "PropertyValue": "海程",
        "LanguageId": 2,
        "TableId": 25
    },
    {
        "Id": 226,
        "EntityType": "Product",
        "PropertyKey": "Name",
        "PropertyValue": "孜绍",
        "LanguageId": 2,
        "TableId": 26
    },
    {
        "Id": 227,
        "EntityType": "Product",
        "PropertyKey": "Name",
        "PropertyValue": "碧萱",
        "LanguageId": 2,
        "TableId": 27
    },
    {
        "Id": 228,
        "EntityType": "Product",
        "PropertyKey": "Name",
        "PropertyValue": "思宇",
        "LanguageId": 2,
        "TableId": 28
    },
    {
        "Id": 229,
        "EntityType": "Product",
        "PropertyKey": "Name",
        "PropertyValue": "思翰",
        "LanguageId": 2,
        "TableId": 29
    },
    {
        "Id": 230,
        "EntityType": "Product",
        "PropertyKey": "Name",
        "PropertyValue": "惠茜",
        "LanguageId": 2,
        "TableId": 30
    },
    {
        "Id": 231,
        "EntityType": "Product",
        "PropertyKey": "Name",
        "PropertyValue": "云哲",
        "LanguageId": 2,
        "TableId": 31
    },
    {
        "Id": 232,
        "EntityType": "Product",
        "PropertyKey": "Name",
        "PropertyValue": "琪煜",
        "LanguageId": 2,
        "TableId": 32
    },
    {
        "Id": 233,
        "EntityType": "Product",
        "PropertyKey": "Name",
        "PropertyValue": "哲恒",
        "LanguageId": 2,
        "TableId": 33
    },
    {
        "Id": 234,
        "EntityType": "Product",
        "PropertyKey": "Name",
        "PropertyValue": "奕漳",
        "LanguageId": 2,
        "TableId": 34
    },
    {
        "Id": 235,
        "EntityType": "Product",
        "PropertyKey": "Name",
        "PropertyValue": "琪煜",
        "LanguageId": 2,
        "TableId": 35
    },
    {
        "Id": 236,
        "EntityType": "Product",
        "PropertyKey": "Name",
        "PropertyValue": "银含",
        "LanguageId": 2,
        "TableId": 36
    },
    {
        "Id": 237,
        "EntityType": "Product",
        "PropertyKey": "Name",
        "PropertyValue": "轩硕",
        "LanguageId": 2,
        "TableId": 37
    },
    {
        "Id": 238,
        "EntityType": "Product",
        "PropertyKey": "Name",
        "PropertyValue": "志宸",
        "LanguageId": 2,
        "TableId": 38
    },
    {
        "Id": 239,
        "EntityType": "Product",
        "PropertyKey": "Name",
        "PropertyValue": "俊泽",
        "LanguageId": 2,
        "TableId": 39
    },
    {
        "Id": 240,
        "EntityType": "Product",
        "PropertyKey": "Name",
        "PropertyValue": "远帆",
        "LanguageId": 2,
        "TableId": 40
    },
    {
        "Id": 241,
        "EntityType": "Product",
        "PropertyKey": "Name",
        "PropertyValue": "丰逸",
        "LanguageId": 2,
        "TableId": 41
    },
    {
        "Id": 242,
        "EntityType": "Product",
        "PropertyKey": "Name",
        "PropertyValue": "培安",
        "LanguageId": 2,
        "TableId": 42
    },
    {
        "Id": 243,
        "EntityType": "Product",
        "PropertyKey": "Name",
        "PropertyValue": "俞凯",
        "LanguageId": 2,
        "TableId": 43
    },
    {
        "Id": 244,
        "EntityType": "Product",
        "PropertyKey": "Name",
        "PropertyValue": "云哲",
        "LanguageId": 2,
        "TableId": 44
    },
    {
        "Id": 245,
        "EntityType": "Product",
        "PropertyKey": "Name",
        "PropertyValue": "秩选",
        "LanguageId": 2,
        "TableId": 45
    },
    {
        "Id": 246,
        "EntityType": "Product",
        "PropertyKey": "Name",
        "PropertyValue": "亦涵",
        "LanguageId": 2,
        "TableId": 46
    },
    {
        "Id": 247,
        "EntityType": "Product",
        "PropertyKey": "Name",
        "PropertyValue": "博裕",
        "LanguageId": 2,
        "TableId": 47
    },
    {
        "Id": 248,
        "EntityType": "Product",
        "PropertyKey": "Name",
        "PropertyValue": "羽彤",
        "LanguageId": 2,
        "TableId": 48
    },
    {
        "Id": 249,
        "EntityType": "Product",
        "PropertyKey": "Name",
        "PropertyValue": "辰华",
        "LanguageId": 2,
        "TableId": 49
    },
    {
        "Id": 250,
        "EntityType": "Product",
        "PropertyKey": "Name",
        "PropertyValue": "澄泓",
        "LanguageId": 2,
        "TableId": 50
    },
    {
        "Id": 251,
        "EntityType": "Product",
        "PropertyKey": "Name",
        "PropertyValue": "雪丽",
        "LanguageId": 2,
        "TableId": 51
    },
    {
        "Id": 252,
        "EntityType": "Product",
        "PropertyKey": "Name",
        "PropertyValue": "梦洁",
        "LanguageId": 2,
        "TableId": 52
    },
    {
        "Id": 253,
        "EntityType": "Product",
        "PropertyKey": "Name",
        "PropertyValue": "哲恒",
        "LanguageId": 2,
        "TableId": 53
    },
    {
        "Id": 254,
        "EntityType": "Product",
        "PropertyKey": "Name",
        "PropertyValue": "清凌",
        "LanguageId": 2,
        "TableId": 54
    },
    {
        "Id": 255,
        "EntityType": "Product",
        "PropertyKey": "Name",
        "PropertyValue": "思宇",
        "LanguageId": 2,
        "TableId": 55
    },
    {
        "Id": 256,
        "EntityType": "Product",
        "PropertyKey": "Name",
        "PropertyValue": "伟宸",
        "LanguageId": 2,
        "TableId": 56
    },
    {
        "Id": 257,
        "EntityType": "Product",
        "PropertyKey": "Name",
        "PropertyValue": "辰华",
        "LanguageId": 2,
        "TableId": 57
    },
    {
        "Id": 258,
        "EntityType": "Product",
        "PropertyKey": "Name",
        "PropertyValue": "梓焓",
        "LanguageId": 2,
        "TableId": 58
    },
    {
        "Id": 259,
        "EntityType": "Product",
        "PropertyKey": "Name",
        "PropertyValue": "明美",
        "LanguageId": 2,
        "TableId": 59
    },
    {
        "Id": 260,
        "EntityType": "Product",
        "PropertyKey": "Name",
        "PropertyValue": "雨萌",
        "LanguageId": 2,
        "TableId": 60
    },
    {
        "Id": 261,
        "EntityType": "Product",
        "PropertyKey": "Name",
        "PropertyValue": "羽彤",
        "LanguageId": 2,
        "TableId": 61
    },
    {
        "Id": 262,
        "EntityType": "Product",
        "PropertyKey": "Name",
        "PropertyValue": "淑颖",
        "LanguageId": 2,
        "TableId": 62
    },
    {
        "Id": 263,
        "EntityType": "Product",
        "PropertyKey": "Name",
        "PropertyValue": "烨伟",
        "LanguageId": 2,
        "TableId": 63
    },
    {
        "Id": 264,
        "EntityType": "Product",
        "PropertyKey": "Name",
        "PropertyValue": "浩成",
        "LanguageId": 2,
        "TableId": 64
    },
    {
        "Id": 265,
        "EntityType": "Product",
        "PropertyKey": "Name",
        "PropertyValue": "晓晴",
        "LanguageId": 2,
        "TableId": 65
    },
    {
        "Id": 266,
        "EntityType": "Product",
        "PropertyKey": "Name",
        "PropertyValue": "永鑫",
        "LanguageId": 2,
        "TableId": 66
    },
    {
        "Id": 267,
        "EntityType": "Product",
        "PropertyKey": "Name",
        "PropertyValue": "宸赫",
        "LanguageId": 2,
        "TableId": 67
    },
    {
        "Id": 268,
        "EntityType": "Product",
        "PropertyKey": "Name",
        "PropertyValue": "俊誉",
        "LanguageId": 2,
        "TableId": 68
    },
    {
        "Id": 269,
        "EntityType": "Product",
        "PropertyKey": "Name",
        "PropertyValue": "宇涵",
        "LanguageId": 2,
        "TableId": 69
    },
    {
        "Id": 270,
        "EntityType": "Product",
        "PropertyKey": "Name",
        "PropertyValue": "萧然",
        "LanguageId": 2,
        "TableId": 70
    },
    {
        "Id": 271,
        "EntityType": "Product",
        "PropertyKey": "Name",
        "PropertyValue": "雪丽",
        "LanguageId": 2,
        "TableId": 71
    },
    {
        "Id": 272,
        "EntityType": "Product",
        "PropertyKey": "Name",
        "PropertyValue": "烨伟",
        "LanguageId": 2,
        "TableId": 72
    },
    {
        "Id": 273,
        "EntityType": "Product",
        "PropertyKey": "Name",
        "PropertyValue": "凰羽",
        "LanguageId": 2,
        "TableId": 73
    },
    {
        "Id": 274,
        "EntityType": "Product",
        "PropertyKey": "Name",
        "PropertyValue": "思宇",
        "LanguageId": 2,
        "TableId": 74
    },
    {
        "Id": 275,
        "EntityType": "Product",
        "PropertyKey": "Name",
        "PropertyValue": "军卿",
        "LanguageId": 2,
        "TableId": 75
    },
    {
        "Id": 276,
        "EntityType": "Product",
        "PropertyKey": "Name",
        "PropertyValue": "梦婷",
        "LanguageId": 2,
        "TableId": 76
    },
    {
        "Id": 277,
        "EntityType": "Product",
        "PropertyKey": "Name",
        "PropertyValue": "宸瑜",
        "LanguageId": 2,
        "TableId": 77
    },
    {
        "Id": 278,
        "EntityType": "Product",
        "PropertyKey": "Name",
        "PropertyValue": "惠茜",
        "LanguageId": 2,
        "TableId": 78
    },
    {
        "Id": 279,
        "EntityType": "Product",
        "PropertyKey": "Name",
        "PropertyValue": "昕磊",
        "LanguageId": 2,
        "TableId": 79
    },
    {
        "Id": 280,
        "EntityType": "Product",
        "PropertyKey": "Name",
        "PropertyValue": "思宇",
        "LanguageId": 2,
        "TableId": 80
    },
    {
        "Id": 281,
        "EntityType": "Product",
        "PropertyKey": "Name",
        "PropertyValue": "清凌",
        "LanguageId": 2,
        "TableId": 81
    },
    {
        "Id": 282,
        "EntityType": "Product",
        "PropertyKey": "Name",
        "PropertyValue": "皓睿",
        "LanguageId": 2,
        "TableId": 82
    },
    {
        "Id": 283,
        "EntityType": "Product",
        "PropertyKey": "Name",
        "PropertyValue": "泽瀚",
        "LanguageId": 2,
        "TableId": 83
    },
    {
        "Id": 284,
        "EntityType": "Product",
        "PropertyKey": "Name",
        "PropertyValue": "秩选",
        "LanguageId": 2,
        "TableId": 84
    },
    {
        "Id": 285,
        "EntityType": "Product",
        "PropertyKey": "Name",
        "PropertyValue": "思宇",
        "LanguageId": 2,
        "TableId": 85
    },
    {
        "Id": 286,
        "EntityType": "Product",
        "PropertyKey": "Name",
        "PropertyValue": "伟菘",
        "LanguageId": 2,
        "TableId": 86
    },
    {
        "Id": 287,
        "EntityType": "Product",
        "PropertyKey": "Name",
        "PropertyValue": "漫妮",
        "LanguageId": 2,
        "TableId": 87
    },
    {
        "Id": 288,
        "EntityType": "Product",
        "PropertyKey": "Name",
        "PropertyValue": "秉皓",
        "LanguageId": 2,
        "TableId": 88
    },
    {
        "Id": 289,
        "EntityType": "Product",
        "PropertyKey": "Name",
        "PropertyValue": "亦涵",
        "LanguageId": 2,
        "TableId": 89
    },
    {
        "Id": 290,
        "EntityType": "Product",
        "PropertyKey": "Name",
        "PropertyValue": "瀚聪",
        "LanguageId": 2,
        "TableId": 90
    },
    {
        "Id": 291,
        "EntityType": "Product",
        "PropertyKey": "Name",
        "PropertyValue": "军卿",
        "LanguageId": 2,
        "TableId": 91
    },
    {
        "Id": 292,
        "EntityType": "Product",
        "PropertyKey": "Name",
        "PropertyValue": "香茹",
        "LanguageId": 2,
        "TableId": 92
    },
    {
        "Id": 293,
        "EntityType": "Product",
        "PropertyKey": "Name",
        "PropertyValue": "俊誉",
        "LanguageId": 2,
        "TableId": 93
    },
    {
        "Id": 294,
        "EntityType": "Product",
        "PropertyKey": "Name",
        "PropertyValue": "娅楠",
        "LanguageId": 2,
        "TableId": 94
    },
    {
        "Id": 295,
        "EntityType": "Product",
        "PropertyKey": "Name",
        "PropertyValue": "彦歆",
        "LanguageId": 2,
        "TableId": 95
    },
    {
        "Id": 296,
        "EntityType": "Product",
        "PropertyKey": "Name",
        "PropertyValue": "宇涵",
        "LanguageId": 2,
        "TableId": 96
    },
    {
        "Id": 297,
        "EntityType": "Product",
        "PropertyKey": "Name",
        "PropertyValue": "钰彤",
        "LanguageId": 2,
        "TableId": 97
    },
    {
        "Id": 298,
        "EntityType": "Product",
        "PropertyKey": "Name",
        "PropertyValue": "可馨",
        "LanguageId": 2,
        "TableId": 98
    },
    {
        "Id": 299,
        "EntityType": "Product",
        "PropertyKey": "Name",
        "PropertyValue": "宸瑜",
        "LanguageId": 2,
        "TableId": 99
    },
    {
        "Id": 300,
        "EntityType": "Product",
        "PropertyKey": "Name",
        "PropertyValue": "银含",
        "LanguageId": 2,
        "TableId": 100
    },
    {
        "Id": 301,
        "EntityType": "Product",
        "PropertyKey": "Description",
        "PropertyValue": "剑波",
        "LanguageId": 2,
        "TableId": 1
    },
    {
        "Id": 302,
        "EntityType": "Product",
        "PropertyKey": "Description",
        "PropertyValue": "茹雪",
        "LanguageId": 2,
        "TableId": 2
    },
    {
        "Id": 303,
        "EntityType": "Product",
        "PropertyKey": "Description",
        "PropertyValue": "泽瀚",
        "LanguageId": 2,
        "TableId": 3
    },
    {
        "Id": 304,
        "EntityType": "Product",
        "PropertyKey": "Description",
        "PropertyValue": "永鑫",
        "LanguageId": 2,
        "TableId": 4
    },
    {
        "Id": 305,
        "EntityType": "Product",
        "PropertyKey": "Description",
        "PropertyValue": "碧萱",
        "LanguageId": 2,
        "TableId": 5
    },
    {
        "Id": 306,
        "EntityType": "Product",
        "PropertyKey": "Description",
        "PropertyValue": "雪怡",
        "LanguageId": 2,
        "TableId": 6
    },
    {
        "Id": 307,
        "EntityType": "Product",
        "PropertyKey": "Description",
        "PropertyValue": "哲恒",
        "LanguageId": 2,
        "TableId": 7
    },
    {
        "Id": 308,
        "EntityType": "Product",
        "PropertyKey": "Description",
        "PropertyValue": "韵寒",
        "LanguageId": 2,
        "TableId": 8
    },
    {
        "Id": 309,
        "EntityType": "Product",
        "PropertyKey": "Description",
        "PropertyValue": "博裕",
        "LanguageId": 2,
        "TableId": 9
    },
    {
        "Id": 310,
        "EntityType": "Product",
        "PropertyKey": "Description",
        "PropertyValue": "璟雯",
        "LanguageId": 2,
        "TableId": 10
    },
    {
        "Id": 311,
        "EntityType": "Product",
        "PropertyKey": "Description",
        "PropertyValue": "晧宇",
        "LanguageId": 2,
        "TableId": 11
    },
    {
        "Id": 312,
        "EntityType": "Product",
        "PropertyKey": "Description",
        "PropertyValue": "秩选",
        "LanguageId": 2,
        "TableId": 12
    },
    {
        "Id": 313,
        "EntityType": "Product",
        "PropertyKey": "Description",
        "PropertyValue": "伟宸",
        "LanguageId": 2,
        "TableId": 13
    },
    {
        "Id": 314,
        "EntityType": "Product",
        "PropertyKey": "Description",
        "PropertyValue": "玺越",
        "LanguageId": 2,
        "TableId": 14
    },
    {
        "Id": 315,
        "EntityType": "Product",
        "PropertyKey": "Description",
        "PropertyValue": "瀚聪",
        "LanguageId": 2,
        "TableId": 15
    },
    {
        "Id": 316,
        "EntityType": "Product",
        "PropertyKey": "Description",
        "PropertyValue": "睿杰",
        "LanguageId": 2,
        "TableId": 16
    },
    {
        "Id": 317,
        "EntityType": "Product",
        "PropertyKey": "Description",
        "PropertyValue": "慧妍",
        "LanguageId": 2,
        "TableId": 17
    },
    {
        "Id": 318,
        "EntityType": "Product",
        "PropertyKey": "Description",
        "PropertyValue": "军卿",
        "LanguageId": 2,
        "TableId": 18
    },
    {
        "Id": 319,
        "EntityType": "Product",
        "PropertyKey": "Description",
        "PropertyValue": "宸瑜",
        "LanguageId": 2,
        "TableId": 19
    },
    {
        "Id": 320,
        "EntityType": "Product",
        "PropertyKey": "Description",
        "PropertyValue": "永鑫",
        "LanguageId": 2,
        "TableId": 20
    },
    {
        "Id": 321,
        "EntityType": "Product",
        "PropertyKey": "Description",
        "PropertyValue": "展博",
        "LanguageId": 2,
        "TableId": 21
    },
    {
        "Id": 322,
        "EntityType": "Product",
        "PropertyKey": "Description",
        "PropertyValue": "鑫蕾",
        "LanguageId": 2,
        "TableId": 22
    },
    {
        "Id": 323,
        "EntityType": "Product",
        "PropertyKey": "Description",
        "PropertyValue": "尹智",
        "LanguageId": 2,
        "TableId": 23
    },
    {
        "Id": 324,
        "EntityType": "Product",
        "PropertyKey": "Description",
        "PropertyValue": "正梅",
        "LanguageId": 2,
        "TableId": 24
    },
    {
        "Id": 325,
        "EntityType": "Product",
        "PropertyKey": "Description",
        "PropertyValue": "凰羽",
        "LanguageId": 2,
        "TableId": 25
    },
    {
        "Id": 326,
        "EntityType": "Product",
        "PropertyKey": "Description",
        "PropertyValue": "宇涵",
        "LanguageId": 2,
        "TableId": 26
    },
    {
        "Id": 327,
        "EntityType": "Product",
        "PropertyKey": "Description",
        "PropertyValue": "尚贤",
        "LanguageId": 2,
        "TableId": 27
    },
    {
        "Id": 328,
        "EntityType": "Product",
        "PropertyKey": "Description",
        "PropertyValue": "远帆",
        "LanguageId": 2,
        "TableId": 28
    },
    {
        "Id": 329,
        "EntityType": "Product",
        "PropertyKey": "Description",
        "PropertyValue": "品逸",
        "LanguageId": 2,
        "TableId": 29
    },
    {
        "Id": 330,
        "EntityType": "Product",
        "PropertyKey": "Description",
        "PropertyValue": "婧涵",
        "LanguageId": 2,
        "TableId": 30
    },
    {
        "Id": 331,
        "EntityType": "Product",
        "PropertyKey": "Description",
        "PropertyValue": "若瑾",
        "LanguageId": 2,
        "TableId": 31
    },
    {
        "Id": 332,
        "EntityType": "Product",
        "PropertyKey": "Description",
        "PropertyValue": "钰彤",
        "LanguageId": 2,
        "TableId": 32
    },
    {
        "Id": 333,
        "EntityType": "Product",
        "PropertyKey": "Description",
        "PropertyValue": "韵寒",
        "LanguageId": 2,
        "TableId": 33
    },
    {
        "Id": 334,
        "EntityType": "Product",
        "PropertyKey": "Description",
        "PropertyValue": "依娜",
        "LanguageId": 2,
        "TableId": 34
    },
    {
        "Id": 335,
        "EntityType": "Product",
        "PropertyKey": "Description",
        "PropertyValue": "琪煜",
        "LanguageId": 2,
        "TableId": 35
    },
    {
        "Id": 336,
        "EntityType": "Product",
        "PropertyKey": "Description",
        "PropertyValue": "宇涵",
        "LanguageId": 2,
        "TableId": 36
    },
    {
        "Id": 337,
        "EntityType": "Product",
        "PropertyKey": "Description",
        "PropertyValue": "宸瑜",
        "LanguageId": 2,
        "TableId": 37
    },
    {
        "Id": 338,
        "EntityType": "Product",
        "PropertyKey": "Description",
        "PropertyValue": "孜绍",
        "LanguageId": 2,
        "TableId": 38
    },
    {
        "Id": 339,
        "EntityType": "Product",
        "PropertyKey": "Description",
        "PropertyValue": "博豪",
        "LanguageId": 2,
        "TableId": 39
    },
    {
        "Id": 340,
        "EntityType": "Product",
        "PropertyKey": "Description",
        "PropertyValue": "正梅",
        "LanguageId": 2,
        "TableId": 40
    },
    {
        "Id": 341,
        "EntityType": "Product",
        "PropertyKey": "Description",
        "PropertyValue": "月松",
        "LanguageId": 2,
        "TableId": 41
    },
    {
        "Id": 342,
        "EntityType": "Product",
        "PropertyKey": "Description",
        "PropertyValue": "品逸",
        "LanguageId": 2,
        "TableId": 42
    },
    {
        "Id": 343,
        "EntityType": "Product",
        "PropertyKey": "Description",
        "PropertyValue": "雪怡",
        "LanguageId": 2,
        "TableId": 43
    },
    {
        "Id": 344,
        "EntityType": "Product",
        "PropertyKey": "Description",
        "PropertyValue": "雅芙",
        "LanguageId": 2,
        "TableId": 44
    },
    {
        "Id": 345,
        "EntityType": "Product",
        "PropertyKey": "Description",
        "PropertyValue": "海程",
        "LanguageId": 2,
        "TableId": 45
    },
    {
        "Id": 346,
        "EntityType": "Product",
        "PropertyKey": "Description",
        "PropertyValue": "清凌",
        "LanguageId": 2,
        "TableId": 46
    },
    {
        "Id": 347,
        "EntityType": "Product",
        "PropertyKey": "Description",
        "PropertyValue": "轩硕",
        "LanguageId": 2,
        "TableId": 47
    },
    {
        "Id": 348,
        "EntityType": "Product",
        "PropertyKey": "Description",
        "PropertyValue": "玺越",
        "LanguageId": 2,
        "TableId": 48
    },
    {
        "Id": 349,
        "EntityType": "Product",
        "PropertyKey": "Description",
        "PropertyValue": "佐仪",
        "LanguageId": 2,
        "TableId": 49
    },
    {
        "Id": 350,
        "EntityType": "Product",
        "PropertyKey": "Description",
        "PropertyValue": "永鑫",
        "LanguageId": 2,
        "TableId": 50
    },
    {
        "Id": 351,
        "EntityType": "Product",
        "PropertyKey": "Description",
        "PropertyValue": "羽彤",
        "LanguageId": 2,
        "TableId": 51
    },
    {
        "Id": 352,
        "EntityType": "Product",
        "PropertyKey": "Description",
        "PropertyValue": "怡香",
        "LanguageId": 2,
        "TableId": 52
    },
    {
        "Id": 353,
        "EntityType": "Product",
        "PropertyKey": "Description",
        "PropertyValue": "志宸",
        "LanguageId": 2,
        "TableId": 53
    },
    {
        "Id": 354,
        "EntityType": "Product",
        "PropertyKey": "Description",
        "PropertyValue": "皓睿",
        "LanguageId": 2,
        "TableId": 54
    },
    {
        "Id": 355,
        "EntityType": "Product",
        "PropertyKey": "Description",
        "PropertyValue": "香茹",
        "LanguageId": 2,
        "TableId": 55
    },
    {
        "Id": 356,
        "EntityType": "Product",
        "PropertyKey": "Description",
        "PropertyValue": "琪煜",
        "LanguageId": 2,
        "TableId": 56
    },
    {
        "Id": 357,
        "EntityType": "Product",
        "PropertyKey": "Description",
        "PropertyValue": "尚贤",
        "LanguageId": 2,
        "TableId": 57
    },
    {
        "Id": 358,
        "EntityType": "Product",
        "PropertyKey": "Description",
        "PropertyValue": "奕漳",
        "LanguageId": 2,
        "TableId": 58
    },
    {
        "Id": 359,
        "EntityType": "Product",
        "PropertyKey": "Description",
        "PropertyValue": "梓彤",
        "LanguageId": 2,
        "TableId": 59
    },
    {
        "Id": 360,
        "EntityType": "Product",
        "PropertyKey": "Description",
        "PropertyValue": "哲恒",
        "LanguageId": 2,
        "TableId": 60
    },
    {
        "Id": 361,
        "EntityType": "Product",
        "PropertyKey": "Description",
        "PropertyValue": "博裕",
        "LanguageId": 2,
        "TableId": 61
    },
    {
        "Id": 362,
        "EntityType": "Product",
        "PropertyKey": "Description",
        "PropertyValue": "俊誉",
        "LanguageId": 2,
        "TableId": 62
    },
    {
        "Id": 363,
        "EntityType": "Product",
        "PropertyKey": "Description",
        "PropertyValue": "琪煜",
        "LanguageId": 2,
        "TableId": 63
    },
    {
        "Id": 364,
        "EntityType": "Product",
        "PropertyKey": "Description",
        "PropertyValue": "笑薇",
        "LanguageId": 2,
        "TableId": 64
    },
    {
        "Id": 365,
        "EntityType": "Product",
        "PropertyKey": "Description",
        "PropertyValue": "莉姿",
        "LanguageId": 2,
        "TableId": 65
    },
    {
        "Id": 366,
        "EntityType": "Product",
        "PropertyKey": "Description",
        "PropertyValue": "龙胜",
        "LanguageId": 2,
        "TableId": 66
    },
    {
        "Id": 367,
        "EntityType": "Product",
        "PropertyKey": "Description",
        "PropertyValue": "志宸",
        "LanguageId": 2,
        "TableId": 67
    },
    {
        "Id": 368,
        "EntityType": "Product",
        "PropertyKey": "Description",
        "PropertyValue": "军卿",
        "LanguageId": 2,
        "TableId": 68
    },
    {
        "Id": 369,
        "EntityType": "Product",
        "PropertyKey": "Description",
        "PropertyValue": "伟宸",
        "LanguageId": 2,
        "TableId": 69
    },
    {
        "Id": 370,
        "EntityType": "Product",
        "PropertyKey": "Description",
        "PropertyValue": "月松",
        "LanguageId": 2,
        "TableId": 70
    },
    {
        "Id": 371,
        "EntityType": "Product",
        "PropertyKey": "Description",
        "PropertyValue": "远帆",
        "LanguageId": 2,
        "TableId": 71
    },
    {
        "Id": 372,
        "EntityType": "Product",
        "PropertyKey": "Description",
        "PropertyValue": "思宇",
        "LanguageId": 2,
        "TableId": 72
    },
    {
        "Id": 373,
        "EntityType": "Product",
        "PropertyKey": "Description",
        "PropertyValue": "雨婷",
        "LanguageId": 2,
        "TableId": 73
    },
    {
        "Id": 374,
        "EntityType": "Product",
        "PropertyKey": "Description",
        "PropertyValue": "宸赫",
        "LanguageId": 2,
        "TableId": 74
    },
    {
        "Id": 375,
        "EntityType": "Product",
        "PropertyKey": "Description",
        "PropertyValue": "孜绍",
        "LanguageId": 2,
        "TableId": 75
    },
    {
        "Id": 376,
        "EntityType": "Product",
        "PropertyKey": "Description",
        "PropertyValue": "雪丽",
        "LanguageId": 2,
        "TableId": 76
    },
    {
        "Id": 377,
        "EntityType": "Product",
        "PropertyKey": "Description",
        "PropertyValue": "秉皓",
        "LanguageId": 2,
        "TableId": 77
    },
    {
        "Id": 378,
        "EntityType": "Product",
        "PropertyKey": "Description",
        "PropertyValue": "宸瑜",
        "LanguageId": 2,
        "TableId": 78
    },
    {
        "Id": 379,
        "EntityType": "Product",
        "PropertyKey": "Description",
        "PropertyValue": "唯枫",
        "LanguageId": 2,
        "TableId": 79
    },
    {
        "Id": 380,
        "EntityType": "Product",
        "PropertyKey": "Description",
        "PropertyValue": "墨含",
        "LanguageId": 2,
        "TableId": 80
    },
    {
        "Id": 381,
        "EntityType": "Product",
        "PropertyKey": "Description",
        "PropertyValue": "尹智",
        "LanguageId": 2,
        "TableId": 81
    },
    {
        "Id": 382,
        "EntityType": "Product",
        "PropertyKey": "Description",
        "PropertyValue": "宇涵",
        "LanguageId": 2,
        "TableId": 82
    },
    {
        "Id": 383,
        "EntityType": "Product",
        "PropertyKey": "Description",
        "PropertyValue": "淑颖",
        "LanguageId": 2,
        "TableId": 83
    },
    {
        "Id": 384,
        "EntityType": "Product",
        "PropertyKey": "Description",
        "PropertyValue": "伟菘",
        "LanguageId": 2,
        "TableId": 84
    },
    {
        "Id": 385,
        "EntityType": "Product",
        "PropertyKey": "Description",
        "PropertyValue": "宸瑜",
        "LanguageId": 2,
        "TableId": 85
    },
    {
        "Id": 386,
        "EntityType": "Product",
        "PropertyKey": "Description",
        "PropertyValue": "晓烽",
        "LanguageId": 2,
        "TableId": 86
    },
    {
        "Id": 387,
        "EntityType": "Product",
        "PropertyKey": "Description",
        "PropertyValue": "云哲",
        "LanguageId": 2,
        "TableId": 87
    },
    {
        "Id": 388,
        "EntityType": "Product",
        "PropertyKey": "Description",
        "PropertyValue": "淑颖",
        "LanguageId": 2,
        "TableId": 88
    },
    {
        "Id": 389,
        "EntityType": "Product",
        "PropertyKey": "Description",
        "PropertyValue": "明美",
        "LanguageId": 2,
        "TableId": 89
    },
    {
        "Id": 390,
        "EntityType": "Product",
        "PropertyKey": "Description",
        "PropertyValue": "浩成",
        "LanguageId": 2,
        "TableId": 90
    },
    {
        "Id": 391,
        "EntityType": "Product",
        "PropertyKey": "Description",
        "PropertyValue": "晓烽",
        "LanguageId": 2,
        "TableId": 91
    },
    {
        "Id": 392,
        "EntityType": "Product",
        "PropertyKey": "Description",
        "PropertyValue": "玺越",
        "LanguageId": 2,
        "TableId": 92
    },
    {
        "Id": 393,
        "EntityType": "Product",
        "PropertyKey": "Description",
        "PropertyValue": "博裕",
        "LanguageId": 2,
        "TableId": 93
    },
    {
        "Id": 394,
        "EntityType": "Product",
        "PropertyKey": "Description",
        "PropertyValue": "梓焓",
        "LanguageId": 2,
        "TableId": 94
    },
    {
        "Id": 395,
        "EntityType": "Product",
        "PropertyKey": "Description",
        "PropertyValue": "宸赫",
        "LanguageId": 2,
        "TableId": 95
    },
    {
        "Id": 396,
        "EntityType": "Product",
        "PropertyKey": "Description",
        "PropertyValue": "晧宇",
        "LanguageId": 2,
        "TableId": 96
    },
    {
        "Id": 397,
        "EntityType": "Product",
        "PropertyKey": "Description",
        "PropertyValue": "彦歆",
        "LanguageId": 2,
        "TableId": 97
    },
    {
        "Id": 398,
        "EntityType": "Product",
        "PropertyKey": "Description",
        "PropertyValue": "烨伟",
        "LanguageId": 2,
        "TableId": 98
    },
    {
        "Id": 399,
        "EntityType": "Product",
        "PropertyKey": "Description",
        "PropertyValue": "雅芙",
        "LanguageId": 2,
        "TableId": 99
    },
    {
        "Id": 400,
        "EntityType": "Product",
        "PropertyKey": "Description",
        "PropertyValue": "晓晴",
        "LanguageId": 2,
        "TableId": 100
    },
    {
        "Id": 401,
        "EntityType": "ProductCategory",
        "PropertyKey": "Name",
        "PropertyValue": "淑颖",
        "LanguageId": 2,
        "TableId": 1
    },
    {
        "Id": 402,
        "EntityType": "ProductCategory",
        "PropertyKey": "Name",
        "PropertyValue": "轩硕",
        "LanguageId": 2,
        "TableId": 2
    },
    {
        "Id": 403,
        "EntityType": "ProductCategory",
        "PropertyKey": "Name",
        "PropertyValue": "轩硕",
        "LanguageId": 2,
        "TableId": 3
    },
    {
        "Id": 404,
        "EntityType": "ProductCategory",
        "PropertyKey": "Name",
        "PropertyValue": "睿杰",
        "LanguageId": 2,
        "TableId": 4
    },
    {
        "Id": 405,
        "EntityType": "ProductCategory",
        "PropertyKey": "Name",
        "PropertyValue": "志宸",
        "LanguageId": 2,
        "TableId": 5
    },
    {
        "Id": 406,
        "EntityType": "ProductCategory",
        "PropertyKey": "Name",
        "PropertyValue": "宸赫",
        "LanguageId": 2,
        "TableId": 6
    },
    {
        "Id": 407,
        "EntityType": "ProductCategory",
        "PropertyKey": "Name",
        "PropertyValue": "惠茜",
        "LanguageId": 2,
        "TableId": 7
    },
    {
        "Id": 408,
        "EntityType": "ProductCategory",
        "PropertyKey": "Name",
        "PropertyValue": "俊誉",
        "LanguageId": 2,
        "TableId": 8
    },
    {
        "Id": 409,
        "EntityType": "ProductCategory",
        "PropertyKey": "Name",
        "PropertyValue": "彤雨",
        "LanguageId": 2,
        "TableId": 9
    },
    {
        "Id": 410,
        "EntityType": "ProductCategory",
        "PropertyKey": "Name",
        "PropertyValue": "尹智",
        "LanguageId": 2,
        "TableId": 10
    },
    {
        "Id": 411,
        "EntityType": "ProductAttribute",
        "PropertyKey": "Name",
        "PropertyValue": "顏色",
        "LanguageId": 2,
        "TableId": 1
    },
    {
        "Id": 412,
        "EntityType": "ProductAttribute",
        "PropertyKey": "Name",
        "PropertyValue": "Color",
        "LanguageId": 1,
        "TableId": 1
    },
    {
        "Id": 413,
        "EntityType": "ProductAttribute",
        "PropertyKey": "Name",
        "PropertyValue": "尺寸",
        "LanguageId": 2,
        "TableId": 2
    },
    {
        "Id": 414,
        "EntityType": "ProductAttribute",
        "PropertyKey": "Name",
        "PropertyValue": "Size",
        "LanguageId": 1,
        "TableId": 2
    }
]